lizard.py
lizardWordCount.py
lizard_langs.py
hfcca-1.10.2.data/scripts/hfcca
hfcca-1.10.2.data/scripts/hfcca.bat
hfcca-1.10.2.data/scripts/lizard
hfcca-1.10.2.data/scripts/lizard.bat
hfcca-1.10.2.dist-info/DESCRIPTION.rst
hfcca-1.10.2.dist-info/METADATA
hfcca-1.10.2.dist-info/RECORD
hfcca-1.10.2.dist-info/WHEEL
hfcca-1.10.2.dist-info/metadata.json
hfcca-1.10.2.dist-info/top_level.txt
languages/__init__.py
languages/java.py
languages/javascript.py
languages/js_style_regex_expression.py
languages/objc.py
languages/python.py
languages/ruby.py
languages/script_language.py
languages/swift.py
languages/tnsdl.py
languages/ttcn.py
lizard_ext/__init__.py
lizard_ext/htmloutput.py
lizard_ext/javascript.py
lizard_ext/keywords.py
lizard_ext/lizardcpre.py
lizard_ext/lizarddependencycount.py
lizard_ext/lizardexitcount.py
lizard_ext/lizardignoreassert.py
lizard_ext/lizardinternalrelationship.py
lizard_ext/lizardmccabe.py
lizard_ext/lizardoutside.py
lizard_ext/lizardwordcount.py
lizard_ext/python.py
lizard_ext/tnsdl.py
lizard_ext/xmloutput.py
lizard_languages/__init__.py
lizard_languages/clike.py
lizard_languages/code_reader.py
lizard_languages/java.py
lizard_languages/javascript.py
lizard_languages/js_style_regex_expression.py
lizard_languages/objc.py
lizard_languages/python.py
lizard_languages/ruby.py
lizard_languages/script_language.py
lizard_languages/swift.py
lizard_languages/tnsdl.py
lizard_languages/ttcn.py
