Metadata-Version: 2.0
Name: hfcca
Version: 1.10.2
Summary: A code analyzer without caring the C/C++ header files.
